setup.cfg
setup.py
socketpy/__init__.py
socketpy/__main__.py
socketpy/analyzer.py
socketpy/commands.py
socketpy/compiler.py
socketpy/configure.py
socketpy/db.py
socketpy/exceptions.py
socketpy/filing.py
socketpy/formatter.py
socketpy/parser.py
socketpy/route.py
socketpy/templates.py
socketpy.egg-info/PKG-INFO
socketpy.egg-info/SOURCES.txt
socketpy.egg-info/dependency_links.txt
socketpy.egg-info/entry_points.txt
socketpy.egg-info/top_level.txt
test/test_analyzer.py
test/test_commands.py
test/test_commands_messages.py
test/test_configurer.py
test/test_filing.py
test/test_parser.py