Metadata-Version: 1.1
Name: socketpy
Version: 0.3.3
Summary: First description for the module
Home-page: https://github.com/fran-bravo/socketpy
Author: Francisco Bravo
Author-email: fran_ase@hotmail.com
License: MIT
Download-URL: https://github.com/fran-bravo/socketpy/tarball/v0.3.3
Keywords: sockets,C
Platform: UNKNOWN
Classifier: Development Status :: 3 - Alpha
